odoo/addons/account_check_date/README.rst
odoo/addons/account_check_date/__init__.py
odoo/addons/account_check_date/__manifest__.py
odoo/addons/account_check_date/hooks.py
odoo/addons/account_check_date/i18n/account_check_date.pot
odoo/addons/account_check_date/i18n/es.po
odoo/addons/account_check_date/models/__init__.py
odoo/addons/account_check_date/models/account_payment.py
odoo/addons/account_check_date/readme/CONTRIBUTORS.rst
odoo/addons/account_check_date/readme/DESCRIPTION.rst
odoo/addons/account_check_date/readme/USAGE.rst
odoo/addons/account_check_date/static/description/icon.png
odoo/addons/account_check_date/static/description/index.html
odoo/addons/account_check_date/views/account_payment_views.xml
odoo/addons/account_check_date/wizard/__init__.py
odoo/addons/account_check_date/wizard/account_payment_register.py
odoo/addons/account_check_date/wizard/account_payment_register_views.xml
odoo14_addon_account_check_date-14.0.1.0.1.dev5.dist-info/METADATA
odoo14_addon_account_check_date-14.0.1.0.1.dev5.dist-info/WHEEL
odoo14_addon_account_check_date-14.0.1.0.1.dev5.dist-info/top_level.txt
odoo14_addon_account_check_date-14.0.1.0.1.dev5.dist-info/RECORD
